[
    {
        "pid": "322568996",
        "brands": [
            "mm6"
        ],
        "name": "mm6 자켓 로고 패치 울 블레이저",
        "price_updates": [
            {
                "1741924255": "298000"
            }
        ],
        "product_image": "https://media.bunjang.co.kr/product/322568996_1_1741863002_w{res}.jpg",
        "status": "0",
        "category_id": "320300400",
        "collected_timestamp": "2025-03-14 06:39:28"
    },
    {
        "pid": "322135169",
        "brands": [
            "mm6"
        ],
        "name": "[52] 마르지엘라 mm6 데님 자켓 흑청",
        "price_updates": [
            {
                "1741911770": "400000"
            }
        ],
        "product_image": "https://media.bunjang.co.kr/product/322135169_1_1741647852_w{res}.jpg",
        "status": "0",
        "category_id": "320300400",
        "collected_timestamp": "2025-03-14 06:39:28"
    },
    {
        "pid": "306720235",
        "brands": [
            "mm6"
        ],
        "name": "mm6 마르지엘라 스웻셔츠",
        "price_updates": [
            {
                "1741870742": "180000"
            }
        ],
        "product_image": "https://media.bunjang.co.kr/product/306720235_1_1736346105_w{res}.jpg",
        "status": "0",
        "category_id": "320210500",
        "collected_timestamp": "2025-03-14 06:39:28"
    },
    {
        "pid": "280082396",
        "brands": [
            "mm6"
        ],
        "name": "마르지엘라 mm6 티셔츠 M",
        "price_updates": [
            {
                "1741880562": "174000"
            }
        ],
        "product_image": "https://media.bunjang.co.kr/product/280082396_1_1730963129_w{res}.jpg",
        "status": "0",
        "category_id": "320210100",
        "collected_timestamp": "2025-03-14 06:39:28"
    },
    {
        "pid": "258498686",
        "brands": [
            "mm6"
        ],
        "name": "mm6 x 오프닝세레모니 가디건",
        "price_updates": [
            {
                "1741886744": "300000"
            }
        ],
        "product_image": "https://media.bunjang.co.kr/product/258498686_1_1739864101_w{res}.jpg",
        "status": "0",
        "category_id": "320300600",
        "collected_timestamp": "2025-03-14 06:39:28"
    },
    {
        "pid": "295437686",
        "brands": [
            "mm6"
        ],
        "name": "mm6 마르지엘라 오버사이즈 코트 40",
        "price_updates": [
            {
                "1741868213": "375000"
            }
        ],
        "product_image": "https://media.bunjang.co.kr/product/295437686_1_1740544061_w{res}.jpg",
        "status": "0",
        "category_id": "320300100",
        "collected_timestamp": "2025-03-14 06:39:28"
    },
    {
        "pid": "245951276",
        "brands": [
            "mm6"
        ],
        "name": "(새상품) 메종 마르지엘라 자켓 블레이저 mm6 스트라이프 금장 자켓",
        "price_updates": [
            {
                "1741863611": "490000"
            }
        ],
        "product_image": "https://media.bunjang.co.kr/product/245951276_1_1737460386_w{res}.jpg",
        "status": "0",
        "category_id": "320300400",
        "collected_timestamp": "2025-03-14 06:39:28"
    },
    {
        "pid": "316223077",
        "brands": [
            "mm6"
        ],
        "name": "슈프림 x mm6 마르지엘라 포일 워크 자켓 XL",
        "price_updates": [
            {
                "1741880429": "800000"
            }
        ],
        "product_image": "https://media.bunjang.co.kr/product/316223077_1_1741880450_w{res}.jpg",
        "status": "0",
        "category_id": "320300400",
        "collected_timestamp": "2025-03-14 06:39:28"
    },
    {
        "pid": "307321408",
        "brands": [
            "mm6"
        ],
        "name": "마르지엘라 mm6 노스페이스 써클 후리스 M사이즈",
        "price_updates": [
            {
                "1741847081": "600000"
            }
        ],
        "product_image": "https://media.bunjang.co.kr/product/307321408_1_1735026612_w{res}.jpg",
        "status": "0",
        "category_id": "320300200",
        "collected_timestamp": "2025-03-14 06:39:28"
    }
]